[
  {
    "direction": "Flat", 
    "noise": 1, 
    "sysTime": "2016-03-26T05:29:28.203-0700", 
    "xDrip_calculated_value": 121, 
    "xDrip_raw": 138, 
    "dateString": "2016-03-26T05:29:28.203-0700", 
    "sgv": 121, 
    "date": 1458995368203, 
    "xDrip_filtered": 143, 
    "xDrip_age_adjusted_raw_value": 138, 
    "unfiltered": 138000, 
    "rssi": 100, 
    "device": "xDrip-DexcomShare", 
    "filtered": 143000, 
    "xDrip_calculated_current_slope": -2.332439231627876e-05, 
    "_id": "56f680ce65110bbfc1928e4c", 
    "type": "sgv"
  }, 
  {
    "direction": "Flat", 
    "noise": 1, 
    "sysTime": "2016-03-26T05:24:28.088-0700", 
    "xDrip_calculated_value": 128, 
    "xDrip_raw": 144, 
    "dateString": "2016-03-26T05:24:28.088-0700", 
    "sgv": 128, 
    "date": 1458995068088, 
    "xDrip_filtered": 144, 
    "xDrip_age_adjusted_raw_value": 144, 
    "unfiltered": 144000, 
    "rssi": 100, 
    "device": "xDrip-DexcomShare", 
    "filtered": 144000, 
    "xDrip_calculated_current_slope": -3.342100777706851e-06, 
    "_id": "56f67f9e65110bbfc1928e4b", 
    "type": "sgv"
  }, 
  {
    "direction": "Flat", 
    "noise": 1, 
    "sysTime": "2016-03-26T05:19:28.875-0700", 
    "xDrip_calculated_value": 129, 
    "xDrip_raw": 144, 
    "dateString": "2016-03-26T05:19:28.875-0700", 
    "sgv": 129, 
    "date": 1458994768875, 
    "xDrip_filtered": 146, 
    "xDrip_age_adjusted_raw_value": 144, 
    "unfiltered": 144000, 
    "rssi": 100, 
    "device": "xDrip-DexcomShare", 
    "filtered": 146000, 
    "xDrip_calculated_current_slope": -3.3332777787036883e-06, 
    "_id": "56f67e9665110bbfc1928e48", 
    "type": "sgv"
  }, 
  {
    "direction": "Flat", 
    "noise": 1, 
    "sysTime": "2016-03-26T05:14:28.870-0700", 
    "xDrip_calculated_value": 130, 
    "xDrip_raw": 145, 
    "dateString": "2016-03-26T05:14:28.870-0700", 
    "sgv": 130, 
    "date": 1458994468870, 
    "xDrip_filtered": 149, 
    "xDrip_age_adjusted_raw_value": 145, 
    "unfiltered": 145000, 
    "rssi": 100, 
    "device": "xDrip-DexcomShare", 
    "filtered": 149000, 
    "xDrip_calculated_current_slope": 0, 
    "_id": "56f67d4565110bbfc1928e47", 
    "type": "sgv"
  }, 
  {
    "direction": "Flat", 
    "noise": 1, 
    "sysTime": "2016-03-26T05:09:28.822-0700", 
    "xDrip_calculated_value": 130, 
    "xDrip_raw": 146, 
    "dateString": "2016-03-26T05:09:28.822-0700", 
    "sgv": 130, 
    "date": 1458994168822, 
    "xDrip_filtered": 151, 
    "xDrip_age_adjusted_raw_value": 146, 
    "unfiltered": 146000, 
    "rssi": 100, 
    "device": "xDrip-DexcomShare", 
    "filtered": 151000, 
    "xDrip_calculated_current_slope": -1.333613392145684e-05, 
    "_id": "56f67c1865110bbfc1928e44", 
    "type": "sgv"
  }, 
  {
    "direction": "Flat", 
    "noise": 1, 
    "sysTime": "2016-03-26T05:04:28.885-0700", 
    "xDrip_calculated_value": 134, 
    "xDrip_raw": 149, 
    "dateString": "2016-03-26T05:04:28.885-0700", 
    "sgv": 134, 
    "date": 1458993868885, 
    "xDrip_filtered": 153, 
    "xDrip_age_adjusted_raw_value": 149, 
    "unfiltered": 149000, 
    "rssi": 100, 
    "device": "xDrip-DexcomShare", 
    "filtered": 153000, 
    "xDrip_calculated_current_slope": -1.6656894621821865e-05, 
    "_id": "56f67b0e65110bbfc1928e43", 
    "type": "sgv"
  }, 
  {
    "direction": "Flat", 
    "noise": 1, 
    "sysTime": "2016-03-26T04:59:28.709-0700", 
    "xDrip_calculated_value": 139, 
    "xDrip_raw": 153, 
    "dateString": "2016-03-26T04:59:28.709-0700", 
    "sgv": 139, 
    "date": 1458993568709, 
    "xDrip_filtered": 153, 
    "xDrip_age_adjusted_raw_value": 153, 
    "unfiltered": 153000, 
    "rssi": 100, 
    "device": "xDrip-DexcomShare", 
    "filtered": 153000, 
    "xDrip_calculated_current_slope": -6.660672061811036e-06, 
    "_id": "56f679c065110bbfc1928e3f", 
    "type": "sgv"
  }, 
  {
    "direction": "Flat", 
    "noise": 1, 
    "sysTime": "2016-03-26T04:54:28.439-0700", 
    "xDrip_calculated_value": 141, 
    "xDrip_raw": 154, 
    "dateString": "2016-03-26T04:54:28.439-0700", 
    "sgv": 141, 
    "date": 1458993268439, 
    "xDrip_filtered": 152, 
    "xDrip_age_adjusted_raw_value": 154, 
    "unfiltered": 154000, 
    "rssi": 100, 
    "device": "xDrip-DexcomShare", 
    "filtered": 152000, 
    "xDrip_calculated_current_slope": 6.653404214266229e-06, 
    "_id": "56f6789365110bbfc1928e3b", 
    "type": "sgv"
  }, 
  {
    "direction": "Flat", 
    "noise": 1, 
    "sysTime": "2016-03-26T04:49:27.841-0700", 
    "xDrip_calculated_value": 139, 
    "xDrip_raw": 153, 
    "dateString": "2016-03-26T04:49:27.841-0700", 
    "sgv": 139, 
    "date": 1458992967841, 
    "xDrip_filtered": 152, 
    "xDrip_age_adjusted_raw_value": 153, 
    "unfiltered": 153000, 
    "rssi": 100, 
    "device": "xDrip-DexcomShare", 
    "filtered": 152000, 
    "xDrip_calculated_current_slope": 6.6862797539449055e-06, 
    "_id": "56f6778965110bbfc1928e37", 
    "type": "sgv"
  }, 
  {
    "direction": "Flat", 
    "noise": 1, 
    "sysTime": "2016-03-26T04:44:28.721-0700", 
    "xDrip_calculated_value": 137, 
    "xDrip_raw": 151, 
    "dateString": "2016-03-26T04:44:28.721-0700", 
    "sgv": 137, 
    "date": 1458992668721, 
    "xDrip_filtered": 152, 
    "xDrip_age_adjusted_raw_value": 151, 
    "unfiltered": 151000, 
    "rssi": 100, 
    "device": "xDrip-DexcomShare", 
    "filtered": 152000, 
    "xDrip_calculated_current_slope": -3.3310793030049667e-06, 
    "_id": "56f6763b65110bbfc1928e36", 
    "type": "sgv"
  }
]