[
  {
    "filtered": 151000, 
    "direction": "Flat", 
    "noise": 1, 
    "raw": 131, 
    "type": "sgv", 
    "_id": "56ed260665110bbfc1927b69", 
    "sysTime": "2016-03-19T03:11:55.323-0700", 
    "dateString": "2016-03-19T03:11:55.323-0700", 
    "sgv": 135, 
    "device": "xDrip-DexcomShare", 
    "xDrip_filtered": 151, 
    "unfiltered": 147000, 
    "xDrip_raw": 147, 
    "date": 1458382315323, 
    "rssi": 100, 
    "xDrip_calculated_current_slope": -1.0002400576138273e-05, 
    "xDrip_age_adjusted_raw_value": 147, 
    "xDrip_calculated_value": 135
  }, 
  {
    "filtered": 155000, 
    "direction": "Flat", 
    "noise": 1, 
    "raw": 133, 
    "type": "sgv", 
    "_id": "56ed24fa65110bbfc1927b68", 
    "sysTime": "2016-03-19T03:06:55.395-0700", 
    "dateString": "2016-03-19T03:06:55.395-0700", 
    "sgv": 138, 
    "device": "xDrip-DexcomShare", 
    "xDrip_filtered": 155, 
    "unfiltered": 150000, 
    "xDrip_raw": 150, 
    "date": 1458382015395, 
    "rssi": 100, 
    "xDrip_calculated_current_slope": -1.3350822911347198e-05, 
    "xDrip_age_adjusted_raw_value": 150, 
    "xDrip_calculated_value": 138
  }, 
  {
    "filtered": 159000, 
    "direction": "FortyFiveDown", 
    "noise": 1, 
    "raw": 136, 
    "type": "sgv", 
    "_id": "56ed23b565110bbfc1927b64", 
    "sysTime": "2016-03-19T03:01:55.788-0700", 
    "dateString": "2016-03-19T03:01:55.788-0700", 
    "sgv": 142, 
    "device": "xDrip-DexcomShare", 
    "xDrip_filtered": 159, 
    "unfiltered": 153000, 
    "xDrip_raw": 153, 
    "date": 1458381715788, 
    "rssi": 100, 
    "xDrip_calculated_current_slope": -9.975195015062545e-06, 
    "xDrip_age_adjusted_raw_value": 153, 
    "xDrip_calculated_value": 142
  }, 
  {
    "filtered": 165000, 
    "direction": "FortyFiveDown", 
    "noise": 1, 
    "raw": 136, 
    "type": "sgv", 
    "_id": "56ed22af65110bbfc1927b63", 
    "sysTime": "2016-03-19T02:56:55.042-0700", 
    "dateString": "2016-03-19T02:56:55.042-0700", 
    "sgv": 145, 
    "device": "xDrip-DexcomShare", 
    "xDrip_filtered": 165, 
    "unfiltered": 156000, 
    "xDrip_raw": 156, 
    "date": 1458381415042, 
    "rssi": 100, 
    "xDrip_calculated_current_slope": -1.9996933803483465e-05, 
    "xDrip_age_adjusted_raw_value": 156, 
    "xDrip_calculated_value": 145
  }, 
  {
    "filtered": 172000, 
    "direction": "FortyFiveDown", 
    "noise": 1, 
    "raw": 141, 
    "type": "sgv", 
    "_id": "56ed215b65110bbfc1927b5f", 
    "sysTime": "2016-03-19T02:51:54.996-0700", 
    "dateString": "2016-03-19T02:51:54.996-0700", 
    "sgv": 151, 
    "device": "xDrip-DexcomShare", 
    "xDrip_filtered": 172, 
    "unfiltered": 162000, 
    "xDrip_raw": 162, 
    "date": 1458381114996, 
    "rssi": 100, 
    "xDrip_calculated_current_slope": -2.332882309420179e-05, 
    "xDrip_age_adjusted_raw_value": 162, 
    "xDrip_calculated_value": 151
  }, 
  {
    "filtered": 178000, 
    "direction": "FortyFiveDown", 
    "noise": 1, 
    "raw": 148, 
    "type": "sgv", 
    "_id": "56ed202f65110bbfc1927b5e", 
    "sysTime": "2016-03-19T02:46:54.938-0700", 
    "dateString": "2016-03-19T02:46:54.938-0700", 
    "sgv": 158, 
    "device": "xDrip-DexcomShare", 
    "xDrip_filtered": 178, 
    "unfiltered": 168000, 
    "xDrip_raw": 168, 
    "date": 1458380814938, 
    "rssi": 100, 
    "xDrip_calculated_current_slope": -1.9981683456831237e-05, 
    "xDrip_age_adjusted_raw_value": 168, 
    "xDrip_calculated_value": 158
  }, 
  {
    "filtered": 185000, 
    "direction": "FortyFiveDown", 
    "noise": 1, 
    "raw": 153, 
    "type": "sgv", 
    "_id": "56ed1f2165110bbfc1927b5a", 
    "sysTime": "2016-03-19T02:41:54.663-0700", 
    "dateString": "2016-03-19T02:41:54.663-0700", 
    "sgv": 164, 
    "device": "xDrip-DexcomShare", 
    "xDrip_filtered": 185, 
    "unfiltered": 174000, 
    "xDrip_raw": 174, 
    "date": 1458380514663, 
    "rssi": 100, 
    "xDrip_calculated_current_slope": -2.6664889007399506e-05, 
    "xDrip_age_adjusted_raw_value": 174, 
    "xDrip_calculated_value": 164
  }, 
  {
    "filtered": 199000, 
    "direction": "FortyFiveDown", 
    "noise": 1, 
    "raw": 169, 
    "type": "sgv", 
    "_id": "56ed1cd065110bbfc1927b59", 
    "sysTime": "2016-03-19T02:31:54.623-0700", 
    "dateString": "2016-03-19T02:31:54.623-0700", 
    "sgv": 180, 
    "device": "xDrip-DexcomShare", 
    "xDrip_filtered": 199, 
    "unfiltered": 188000, 
    "xDrip_raw": 188, 
    "date": 1458379914623, 
    "rssi": 100, 
    "xDrip_calculated_current_slope": -2.6652984801135417e-05, 
    "xDrip_age_adjusted_raw_value": 188, 
    "xDrip_calculated_value": 180
  }, 
  {
    "filtered": 206000, 
    "direction": "FortyFiveDown", 
    "noise": 1, 
    "raw": 178, 
    "type": "sgv", 
    "_id": "56ed1b7f65110bbfc1927b58", 
    "sysTime": "2016-03-19T02:26:54.469-0700", 
    "dateString": "2016-03-19T02:26:54.469-0700", 
    "sgv": 188, 
    "device": "xDrip-DexcomShare", 
    "xDrip_filtered": 206, 
    "unfiltered": 196000, 
    "xDrip_raw": 196, 
    "date": 1458379614469, 
    "rssi": 100, 
    "xDrip_calculated_current_slope": -2.0018149789142157e-05, 
    "xDrip_age_adjusted_raw_value": 196, 
    "xDrip_calculated_value": 188
  }, 
  {
    "filtered": 212000, 
    "direction": "FortyFiveDown", 
    "noise": 1, 
    "raw": 183, 
    "type": "sgv", 
    "_id": "56ed1a7665110bbfc1927b57", 
    "sysTime": "2016-03-19T02:21:54.741-0700", 
    "dateString": "2016-03-19T02:21:54.741-0700", 
    "sgv": 194, 
    "device": "xDrip-DexcomShare", 
    "xDrip_filtered": 212, 
    "unfiltered": 201000, 
    "xDrip_raw": 201, 
    "date": 1458379314741, 
    "rssi": 100, 
    "xDrip_calculated_current_slope": -2.3356845891530806e-05, 
    "xDrip_age_adjusted_raw_value": 201, 
    "xDrip_calculated_value": 194
  }
]