[
  {
    "filtered": 196000, 
    "direction": "Flat", 
    "noise": 1, 
    "raw": 183, 
    "type": "sgv", 
    "_id": "56d939d1a3f298555f028f0d", 
    "sysTime": "2016-03-03T23:30:59.581-0800", 
    "dateString": "2016-03-03T23:30:59.581-0800", 
    "sgv": 188, 
    "device": "xDrip-DexcomShare", 
    "xDrip_filtered": 196, 
    "unfiltered": 191000, 
    "xDrip_raw": 191, 
    "date": 1457076659581, 
    "rssi": 100, 
    "xDrip_calculated_current_slope": -9.998566872081668e-06, 
    "xDrip_age_adjusted_raw_value": 191, 
    "xDrip_calculated_value": 188
  }, 
  {
    "filtered": 200000, 
    "direction": "Flat", 
    "noise": 1, 
    "raw": 184, 
    "type": "sgv", 
    "_id": "56d938c8a3f298555f028f0c", 
    "sysTime": "2016-03-03T23:25:59.538-0800", 
    "dateString": "2016-03-03T23:25:59.538-0800", 
    "sgv": 191, 
    "device": "xDrip-DexcomShare", 
    "xDrip_filtered": 200, 
    "unfiltered": 194000, 
    "xDrip_raw": 194, 
    "date": 1457076359538, 
    "rssi": 100, 
    "xDrip_calculated_current_slope": -1.3336222848283794e-05, 
    "xDrip_age_adjusted_raw_value": 194, 
    "xDrip_calculated_value": 191
  }, 
  {
    "filtered": 202000, 
    "direction": "Flat", 
    "noise": 1, 
    "raw": 190, 
    "type": "sgv", 
    "_id": "56d93778a3f298555f028f0b", 
    "sysTime": "2016-03-03T23:20:59.603-0800", 
    "dateString": "2016-03-03T23:20:59.603-0800", 
    "sgv": 195, 
    "device": "xDrip-DexcomShare", 
    "xDrip_filtered": 202, 
    "unfiltered": 197000, 
    "xDrip_raw": 197, 
    "date": 1457076059603, 
    "rssi": 100, 
    "xDrip_calculated_current_slope": -1.3317086487818195e-05, 
    "xDrip_age_adjusted_raw_value": 197, 
    "xDrip_calculated_value": 195
  }, 
  {
    "filtered": 202000, 
    "direction": "Flat", 
    "noise": 1, 
    "raw": 198, 
    "type": "sgv", 
    "_id": "56d9364ca3f298555f028f0a", 
    "sysTime": "2016-03-03T23:15:59.237-0800", 
    "dateString": "2016-03-03T23:15:59.237-0800", 
    "sgv": 199, 
    "device": "xDrip-DexcomShare", 
    "xDrip_filtered": 202, 
    "unfiltered": 201000, 
    "xDrip_raw": 201, 
    "date": 1457075759237, 
    "rssi": 100, 
    "xDrip_calculated_current_slope": -6.668155888148353e-06, 
    "xDrip_age_adjusted_raw_value": 201, 
    "xDrip_calculated_value": 199
  }, 
  {
    "filtered": 201000, 
    "direction": "Flat", 
    "noise": 1, 
    "raw": 202, 
    "type": "sgv", 
    "_id": "56d93542a3f298555f028f09", 
    "sysTime": "2016-03-03T23:10:59.304-0800", 
    "dateString": "2016-03-03T23:10:59.304-0800", 
    "sgv": 201, 
    "device": "xDrip-DexcomShare", 
    "xDrip_filtered": 201, 
    "unfiltered": 202000, 
    "xDrip_raw": 202, 
    "date": 1457075459304, 
    "rssi": 100, 
    "xDrip_calculated_current_slope": 0, 
    "xDrip_age_adjusted_raw_value": 202, 
    "xDrip_calculated_value": 201
  }, 
  {
    "filtered": 199000, 
    "direction": "Flat", 
    "noise": 1, 
    "raw": 204, 
    "type": "sgv", 
    "_id": "56d933f3a3f298555f028f08", 
    "sysTime": "2016-03-03T23:05:59.370-0800", 
    "dateString": "2016-03-03T23:05:59.370-0800", 
    "sgv": 201, 
    "device": "xDrip-DexcomShare", 
    "xDrip_filtered": 199, 
    "unfiltered": 202000, 
    "xDrip_raw": 202, 
    "date": 1457075159370, 
    "rssi": 100, 
    "xDrip_calculated_current_slope": 6.665533525967252e-06, 
    "xDrip_age_adjusted_raw_value": 202, 
    "xDrip_calculated_value": 201
  }, 
  {
    "filtered": 197000, 
    "direction": "Flat", 
    "noise": 1, 
    "raw": 204, 
    "type": "sgv", 
    "_id": "56d932c7a3f298555f028f07", 
    "sysTime": "2016-03-03T23:00:59.319-0800", 
    "dateString": "2016-03-03T23:00:59.319-0800", 
    "sgv": 199, 
    "device": "xDrip-DexcomShare", 
    "xDrip_filtered": 197, 
    "unfiltered": 201000, 
    "xDrip_raw": 201, 
    "date": 1457074859319, 
    "rssi": 100, 
    "xDrip_calculated_current_slope": 9.986484957024827e-06, 
    "xDrip_age_adjusted_raw_value": 201, 
    "xDrip_calculated_value": 199
  }, 
  {
    "filtered": 196000, 
    "direction": "Flat", 
    "noise": 1, 
    "raw": 198, 
    "type": "sgv", 
    "_id": "56d931bda3f298555f028f06", 
    "sysTime": "2016-03-03T22:55:58.913-0800", 
    "dateString": "2016-03-03T22:55:58.913-0800", 
    "sgv": 196, 
    "device": "xDrip-DexcomShare", 
    "xDrip_filtered": 196, 
    "unfiltered": 198000, 
    "xDrip_raw": 198, 
    "date": 1457074558913, 
    "rssi": 100, 
    "xDrip_calculated_current_slope": 1.0002200484106503e-05, 
    "xDrip_age_adjusted_raw_value": 198, 
    "xDrip_calculated_value": 196
  }, 
  {
    "filtered": 193000, 
    "direction": "Flat", 
    "noise": 1, 
    "raw": 195, 
    "type": "sgv", 
    "_id": "56d9306fa3f298555f028f05", 
    "sysTime": "2016-03-03T22:50:58.979-0800", 
    "dateString": "2016-03-03T22:50:58.979-0800", 
    "sgv": 193, 
    "device": "xDrip-DexcomShare", 
    "xDrip_filtered": 193, 
    "unfiltered": 195000, 
    "xDrip_raw": 195, 
    "date": 1457074258979, 
    "rssi": 100, 
    "xDrip_calculated_current_slope": 6.6666222225185165e-06, 
    "xDrip_age_adjusted_raw_value": 195, 
    "xDrip_calculated_value": 193
  }, 
  {
    "filtered": 189000, 
    "direction": "Flat", 
    "noise": 1, 
    "raw": 197, 
    "type": "sgv", 
    "_id": "56d92f42a3f298555f028f02", 
    "sysTime": "2016-03-03T22:45:58.977-0800", 
    "dateString": "2016-03-03T22:45:58.977-0800", 
    "sgv": 191, 
    "device": "xDrip-DexcomShare", 
    "xDrip_filtered": 189, 
    "unfiltered": 194000, 
    "xDrip_raw": 194, 
    "date": 1457073958977, 
    "rssi": 100, 
    "xDrip_calculated_current_slope": -3.3327778703549408e-06, 
    "xDrip_age_adjusted_raw_value": 194, 
    "xDrip_calculated_value": 191
  }
]