[
  {
    "filtered": 112000, 
    "direction": "Flat", 
    "noise": 1, 
    "raw": 123, 
    "type": "sgv", 
    "_id": "56e04332a3f298555f029e89", 
    "sysTime": "2016-03-09T07:35:36.904-0800", 
    "dateString": "2016-03-09T07:35:36.904-0800", 
    "sgv": 114, 
    "device": "xDrip-DexcomShare", 
    "xDrip_filtered": 112, 
    "unfiltered": 121000, 
    "xDrip_raw": 121, 
    "date": 1457537736904, 
    "rssi": 100, 
    "xDrip_calculated_current_slope": 2.3379234563860378e-05, 
    "xDrip_age_adjusted_raw_value": 121, 
    "xDrip_calculated_value": 114
  }, 
  {
    "filtered": 109000, 
    "direction": "Flat", 
    "noise": 1, 
    "raw": 112, 
    "type": "sgv", 
    "_id": "56e041b9a3f298555f029e88", 
    "sysTime": "2016-03-09T07:30:37.493-0800", 
    "dateString": "2016-03-09T07:30:37.493-0800", 
    "sgv": 107, 
    "device": "xDrip-DexcomShare", 
    "xDrip_filtered": 109, 
    "unfiltered": 114000, 
    "xDrip_raw": 114, 
    "date": 1457537437493, 
    "rssi": 100, 
    "xDrip_calculated_current_slope": 1.666400042659841e-05, 
    "xDrip_age_adjusted_raw_value": 114, 
    "xDrip_calculated_value": 107
  }, 
  {
    "filtered": 107000, 
    "direction": "Flat", 
    "noise": 1, 
    "raw": 104, 
    "type": "sgv", 
    "_id": "56e040b3a3f298555f029e87", 
    "sysTime": "2016-03-09T07:25:37.445-0800", 
    "dateString": "2016-03-09T07:25:37.445-0800", 
    "sgv": 102, 
    "device": "xDrip-DexcomShare", 
    "xDrip_filtered": 107, 
    "unfiltered": 109000, 
    "xDrip_raw": 109, 
    "date": 1457537137445, 
    "rssi": 100, 
    "xDrip_calculated_current_slope": 3.3340557120709486e-06, 
    "xDrip_age_adjusted_raw_value": 109, 
    "xDrip_calculated_value": 102
  }, 
  {
    "filtered": 105000, 
    "direction": "Flat", 
    "noise": 1, 
    "raw": 105, 
    "type": "sgv", 
    "_id": "56e03f63a3f298555f029e86", 
    "sysTime": "2016-03-09T07:20:37.510-0800", 
    "dateString": "2016-03-09T07:20:37.510-0800", 
    "sgv": 101, 
    "device": "xDrip-DexcomShare", 
    "xDrip_filtered": 105, 
    "unfiltered": 109000, 
    "xDrip_raw": 109, 
    "date": 1457536837510, 
    "rssi": 100, 
    "xDrip_calculated_current_slope": 6.666533335999947e-06, 
    "xDrip_age_adjusted_raw_value": 109, 
    "xDrip_calculated_value": 101
  }, 
  {
    "filtered": 105000, 
    "direction": "Flat", 
    "noise": 1, 
    "raw": 100, 
    "type": "sgv", 
    "_id": "56e03e37a3f298555f029e82", 
    "sysTime": "2016-03-09T07:15:37.504-0800", 
    "dateString": "2016-03-09T07:15:37.504-0800", 
    "sgv": 99, 
    "device": "xDrip-DexcomShare", 
    "xDrip_filtered": 105, 
    "unfiltered": 106000, 
    "xDrip_raw": 106, 
    "date": 1457536537504, 
    "rssi": 100, 
    "xDrip_calculated_current_slope": 6.68462602859683e-06, 
    "xDrip_age_adjusted_raw_value": 106, 
    "xDrip_calculated_value": 99
  }, 
  {
    "filtered": 105000, 
    "direction": "Flat", 
    "noise": 1, 
    "raw": 97, 
    "type": "sgv", 
    "_id": "56e03d2ea3f298555f029e81", 
    "sysTime": "2016-03-09T07:10:38.310-0800", 
    "dateString": "2016-03-09T07:10:38.310-0800", 
    "sgv": 97, 
    "device": "xDrip-DexcomShare", 
    "xDrip_filtered": 105, 
    "unfiltered": 105000, 
    "xDrip_raw": 105, 
    "date": 1457536238310, 
    "rssi": 100, 
    "xDrip_calculated_current_slope": 6.68462602859683e-06, 
    "xDrip_age_adjusted_raw_value": 105, 
    "xDrip_calculated_value": 97
  }, 
  {
    "filtered": 107000, 
    "direction": "Flat", 
    "noise": 1, 
    "raw": 96, 
    "type": "sgv", 
    "_id": "56e03bdfa3f298555f029e80", 
    "sysTime": "2016-03-09T07:05:37.598-0800", 
    "dateString": "2016-03-09T07:05:37.598-0800", 
    "sgv": 98, 
    "device": "xDrip-DexcomShare", 
    "xDrip_filtered": 107, 
    "unfiltered": 105000, 
    "xDrip_raw": 105, 
    "date": 1457535937598, 
    "rssi": 100, 
    "xDrip_calculated_current_slope": 0, 
    "xDrip_age_adjusted_raw_value": 105, 
    "xDrip_calculated_value": 98
  }, 
  {
    "filtered": 109000, 
    "direction": "Flat", 
    "noise": 1, 
    "raw": 94, 
    "type": "sgv", 
    "_id": "56e03ab2a3f298555f029e7f", 
    "sysTime": "2016-03-09T07:00:37.765-0800", 
    "dateString": "2016-03-09T07:00:37.765-0800", 
    "sgv": 98, 
    "device": "xDrip-DexcomShare", 
    "xDrip_filtered": 109, 
    "unfiltered": 105000, 
    "xDrip_raw": 105, 
    "date": 1457535637765, 
    "rssi": 100, 
    "xDrip_calculated_current_slope": -3.323981864354948e-06, 
    "xDrip_age_adjusted_raw_value": 105, 
    "xDrip_calculated_value": 98
  }, 
  {
    "filtered": 111000, 
    "direction": "Flat", 
    "noise": 1, 
    "raw": 94, 
    "type": "sgv", 
    "_id": "56e039baa3f298555f029e7e", 
    "sysTime": "2016-03-09T06:55:36.921-0800", 
    "dateString": "2016-03-09T06:55:36.921-0800", 
    "sgv": 99, 
    "device": "xDrip-DexcomShare", 
    "xDrip_filtered": 111, 
    "unfiltered": 106000, 
    "xDrip_raw": 106, 
    "date": 1457535336921, 
    "rssi": 100, 
    "xDrip_calculated_current_slope": -1.3373632546072164e-05, 
    "xDrip_age_adjusted_raw_value": 106, 
    "xDrip_calculated_value": 99
  }, 
  {
    "filtered": 111000, 
    "direction": "Flat", 
    "noise": 1, 
    "raw": 103, 
    "type": "sgv", 
    "_id": "56e0385aa3f298555f029e79", 
    "sysTime": "2016-03-09T06:50:37.825-0800", 
    "dateString": "2016-03-09T06:50:37.825-0800", 
    "sgv": 103, 
    "device": "xDrip-DexcomShare", 
    "xDrip_filtered": 111, 
    "unfiltered": 111000, 
    "xDrip_raw": 111, 
    "date": 1457535037825, 
    "rssi": 100, 
    "xDrip_calculated_current_slope": -3.3241918058671984e-06, 
    "xDrip_age_adjusted_raw_value": 111, 
    "xDrip_calculated_value": 103
  }
]