[
  {
    "filtered": 121000, 
    "direction": "Flat", 
    "noise": 1, 
    "raw": 89, 
    "type": "sgv", 
    "_id": "56e44a3da3f298555f02a6ce", 
    "sysTime": "2016-03-12T08:55:25.817-0800", 
    "dateString": "2016-03-12T08:55:25.817-0800", 
    "sgv": 94, 
    "device": "xDrip-DexcomShare", 
    "xDrip_filtered": 121, 
    "unfiltered": 116000, 
    "xDrip_raw": 116, 
    "date": 1457801725817, 
    "rssi": 100, 
    "xDrip_calculated_current_slope": -6.6603171643033644e-06, 
    "xDrip_age_adjusted_raw_value": 116, 
    "xDrip_calculated_value": 94
  }, 
  {
    "filtered": 127000, 
    "direction": "Flat", 
    "noise": 1, 
    "raw": 91, 
    "type": "sgv", 
    "_id": "56e447c6a3f298555f02a6cb", 
    "sysTime": "2016-03-12T08:45:25.245-0800", 
    "dateString": "2016-03-12T08:45:25.245-0800", 
    "sgv": 98, 
    "device": "xDrip-DexcomShare", 
    "xDrip_filtered": 127, 
    "unfiltered": 120000, 
    "xDrip_raw": 120, 
    "date": 1457801125245, 
    "rssi": 100, 
    "xDrip_calculated_current_slope": -2.6692113147867633e-05, 
    "xDrip_age_adjusted_raw_value": 120, 
    "xDrip_calculated_value": 98
  }, 
  {
    "filtered": 129000, 
    "direction": "Flat", 
    "noise": 1, 
    "raw": 104, 
    "type": "sgv", 
    "_id": "56e446bda3f298555f02a6ca", 
    "sysTime": "2016-03-12T08:40:25.531-0800", 
    "dateString": "2016-03-12T08:40:25.531-0800", 
    "sgv": 106, 
    "device": "xDrip-DexcomShare", 
    "xDrip_filtered": 129, 
    "unfiltered": 127000, 
    "xDrip_raw": 127, 
    "date": 1457800825531, 
    "rssi": 100, 
    "xDrip_calculated_current_slope": -9.991008092716555e-06, 
    "xDrip_age_adjusted_raw_value": 127, 
    "xDrip_calculated_value": 106
  }, 
  {
    "filtered": 130000, 
    "direction": "Flat", 
    "noise": 1, 
    "raw": 108, 
    "type": "sgv", 
    "_id": "56e4456da3f298555f02a6c9", 
    "sysTime": "2016-03-12T08:35:25.261-0800", 
    "dateString": "2016-03-12T08:35:25.261-0800", 
    "sgv": 109, 
    "device": "xDrip-DexcomShare", 
    "xDrip_filtered": 130, 
    "unfiltered": 129000, 
    "xDrip_raw": 129, 
    "date": 1457800525261, 
    "rssi": 100, 
    "xDrip_calculated_current_slope": -3.338017684817694e-06, 
    "xDrip_age_adjusted_raw_value": 129, 
    "xDrip_calculated_value": 109
  }, 
  {
    "filtered": 132000, 
    "direction": "Flat", 
    "noise": 1, 
    "raw": 107, 
    "type": "sgv", 
    "_id": "56e44465a3f298555f02a6c8", 
    "sysTime": "2016-03-12T08:30:25.682-0800", 
    "dateString": "2016-03-12T08:30:25.682-0800", 
    "sgv": 110, 
    "device": "xDrip-DexcomShare", 
    "xDrip_filtered": 132, 
    "unfiltered": 129000, 
    "xDrip_raw": 129, 
    "date": 1457800225682, 
    "rssi": 100, 
    "xDrip_calculated_current_slope": -3.338887015402286e-06, 
    "xDrip_age_adjusted_raw_value": 129, 
    "xDrip_calculated_value": 110
  }, 
  {
    "filtered": 133000, 
    "direction": "Flat", 
    "noise": 1, 
    "raw": 108, 
    "type": "sgv", 
    "_id": "56e44314a3f298555f02a6c4", 
    "sysTime": "2016-03-12T08:25:26.181-0800", 
    "dateString": "2016-03-12T08:25:26.181-0800", 
    "sgv": 111, 
    "device": "xDrip-DexcomShare", 
    "xDrip_filtered": 133, 
    "unfiltered": 130000, 
    "xDrip_raw": 130, 
    "date": 1457799926181, 
    "rssi": 100, 
    "xDrip_calculated_current_slope": -9.990875000832574e-06, 
    "xDrip_age_adjusted_raw_value": 130, 
    "xDrip_calculated_value": 111
  }, 
  {
    "filtered": 134000, 
    "direction": "Flat", 
    "noise": 1, 
    "raw": 113, 
    "type": "sgv", 
    "_id": "56e441e7a3f298555f02a6c0", 
    "sysTime": "2016-03-12T08:20:25.907-0800", 
    "dateString": "2016-03-12T08:20:25.907-0800", 
    "sgv": 114, 
    "device": "xDrip-DexcomShare", 
    "xDrip_filtered": 134, 
    "unfiltered": 133000, 
    "xDrip_raw": 133, 
    "date": 1457799625907, 
    "rssi": 100, 
    "xDrip_calculated_current_slope": -3.326713174116841e-06, 
    "xDrip_age_adjusted_raw_value": 133, 
    "xDrip_calculated_value": 114
  }, 
  {
    "filtered": 135000, 
    "direction": "Flat", 
    "noise": 1, 
    "raw": 114, 
    "type": "sgv", 
    "_id": "56e440dea3f298555f02a6bc", 
    "sysTime": "2016-03-12T08:15:25.310-0800", 
    "dateString": "2016-03-12T08:15:25.310-0800", 
    "sgv": 115, 
    "device": "xDrip-DexcomShare", 
    "xDrip_filtered": 135, 
    "unfiltered": 134000, 
    "xDrip_raw": 134, 
    "date": 1457799325310, 
    "rssi": 100, 
    "xDrip_calculated_current_slope": -3.339879497147743e-06, 
    "xDrip_age_adjusted_raw_value": 134, 
    "xDrip_calculated_value": 115
  }, 
  {
    "filtered": 135000, 
    "direction": "Flat", 
    "noise": 1, 
    "raw": 116, 
    "type": "sgv", 
    "_id": "56e43f8fa3f298555f02a6bb", 
    "sysTime": "2016-03-12T08:10:25.898-0800", 
    "dateString": "2016-03-12T08:10:25.898-0800", 
    "sgv": 116, 
    "device": "xDrip-DexcomShare", 
    "xDrip_filtered": 135, 
    "unfiltered": 135000, 
    "xDrip_raw": 135, 
    "date": 1457799025898, 
    "rssi": 100, 
    "xDrip_calculated_current_slope": -3.329637435779618e-06, 
    "xDrip_age_adjusted_raw_value": 135, 
    "xDrip_calculated_value": 116
  }, 
  {
    "filtered": 136000, 
    "direction": "Flat", 
    "noise": 1, 
    "raw": 116, 
    "type": "sgv", 
    "_id": "56e43e63a3f298555f02a6ba", 
    "sysTime": "2016-03-12T08:05:25.565-0800", 
    "dateString": "2016-03-12T08:05:25.565-0800", 
    "sgv": 117, 
    "device": "xDrip-DexcomShare", 
    "xDrip_filtered": 136, 
    "unfiltered": 135000, 
    "xDrip_raw": 135, 
    "date": 1457798725565, 
    "rssi": 100, 
    "xDrip_calculated_current_slope": -3.3357573169836747e-06, 
    "xDrip_age_adjusted_raw_value": 135, 
    "xDrip_calculated_value": 117
  }
]