[
  {
    "_type": "TempBasalDuration", 
    "_description": "TempBasalDuration 2016-03-22T23:22:11 head[2], body[0] op[0x16]", 
    "timestamp": "2016-03-22T23:22:11-07:00", 
    "_body": "", 
    "_head": "1601", 
    "duration (min)": 30, 
    "_date": "0bd6175610"
  }, 
  {
    "_type": "TempBasal", 
    "temp": "absolute", 
    "_description": "TempBasal 2016-03-22T23:22:11 head[2], body[1] op[0x33]", 
    "timestamp": "2016-03-22T23:22:11-07:00", 
    "_body": "00", 
    "_head": "3324", 
    "rate": 0.9, 
    "_date": "0bd6175610"
  }, 
  {
    "_type": "TempBasalDuration", 
    "_description": "TempBasalDuration 2016-03-22T23:22:09 head[2], body[0] op[0x16]", 
    "timestamp": "2016-03-22T23:22:09-07:00", 
    "_body": "", 
    "_head": "1601", 
    "duration (min)": 30, 
    "_date": "09d6175610"
  }, 
  {
    "_type": "TempBasal", 
    "temp": "absolute", 
    "_description": "TempBasal 2016-03-22T23:22:09 head[2], body[1] op[0x33]", 
    "timestamp": "2016-03-22T23:22:09-07:00", 
    "_body": "00", 
    "_head": "3324", 
    "rate": 0.9, 
    "_date": "09d6175610"
  }, 
  {
    "_type": "TempBasalDuration", 
    "_description": "TempBasalDuration 2016-03-22T23:22:08 head[2], body[0] op[0x16]", 
    "timestamp": "2016-03-22T23:22:08-07:00", 
    "_body": "", 
    "_head": "1601", 
    "duration (min)": 30, 
    "_date": "08d6175610"
  }, 
  {
    "_type": "TempBasal", 
    "temp": "absolute", 
    "_description": "TempBasal 2016-03-22T23:22:08 head[2], body[1] op[0x33]", 
    "timestamp": "2016-03-22T23:22:08-07:00", 
    "_body": "00", 
    "_head": "3324", 
    "rate": 0.9, 
    "_date": "08d6175610"
  }, 
  {
    "_type": "TempBasalDuration", 
    "_description": "TempBasalDuration 2016-03-22T23:04:09 head[2], body[0] op[0x16]", 
    "timestamp": "2016-03-22T23:04:09-07:00", 
    "_body": "", 
    "_head": "1601", 
    "duration (min)": 30, 
    "_date": "09c4175610"
  }, 
  {
    "_type": "TempBasal", 
    "temp": "absolute", 
    "_description": "TempBasal 2016-03-22T23:04:09 head[2], body[1] op[0x33]", 
    "timestamp": "2016-03-22T23:04:09-07:00", 
    "_body": "00", 
    "_head": "3300", 
    "rate": 0.0, 
    "_date": "09c4175610"
  }, 
  {
    "_type": "TempBasalDuration", 
    "_description": "TempBasalDuration 2016-03-22T23:04:07 head[2], body[0] op[0x16]", 
    "timestamp": "2016-03-22T23:04:07-07:00", 
    "_body": "", 
    "_head": "1601", 
    "duration (min)": 30, 
    "_date": "07c4175610"
  }, 
  {
    "_type": "TempBasal", 
    "temp": "absolute", 
    "_description": "TempBasal 2016-03-22T23:04:07 head[2], body[1] op[0x33]", 
    "timestamp": "2016-03-22T23:04:07-07:00", 
    "_body": "00", 
    "_head": "3300", 
    "rate": 0.0, 
    "_date": "07c4175610"
  }, 
  {
    "_type": "TempBasalDuration", 
    "_description": "TempBasalDuration 2016-03-22T23:04:06 head[2], body[0] op[0x16]", 
    "timestamp": "2016-03-22T23:04:06-07:00", 
    "_body": "", 
    "_head": "1601", 
    "duration (min)": 30, 
    "_date": "06c4175610"
  }, 
  {
    "_type": "TempBasal", 
    "temp": "absolute", 
    "_description": "TempBasal 2016-03-22T23:04:06 head[2], body[1] op[0x33]", 
    "timestamp": "2016-03-22T23:04:06-07:00", 
    "_body": "00", 
    "_head": "3300", 
    "rate": 0.0, 
    "_date": "06c4175610"
  }, 
  {
    "_type": "TempBasalDuration", 
    "_description": "TempBasalDuration 2016-03-22T22:57:40 head[2], body[0] op[0x16]", 
    "timestamp": "2016-03-22T22:57:40-07:00", 
    "_body": "", 
    "_head": "1601", 
    "duration (min)": 30, 
    "_date": "28f9165610"
  }, 
  {
    "_type": "TempBasal", 
    "temp": "absolute", 
    "_description": "TempBasal 2016-03-22T22:57:40 head[2], body[1] op[0x33]", 
    "timestamp": "2016-03-22T22:57:40-07:00", 
    "_body": "00", 
    "_head": "3308", 
    "rate": 0.2, 
    "_date": "28f9165610"
  }, 
  {
    "_type": "TempBasalDuration", 
    "_description": "TempBasalDuration 2016-03-22T22:57:38 head[2], body[0] op[0x16]", 
    "timestamp": "2016-03-22T22:57:38-07:00", 
    "_body": "", 
    "_head": "1601", 
    "duration (min)": 30, 
    "_date": "26f9165610"
  }, 
  {
    "_type": "TempBasal", 
    "temp": "absolute", 
    "_description": "TempBasal 2016-03-22T22:57:38 head[2], body[1] op[0x33]", 
    "timestamp": "2016-03-22T22:57:38-07:00", 
    "_body": "00", 
    "_head": "3308", 
    "rate": 0.2, 
    "_date": "26f9165610"
  }, 
  {
    "_type": "TempBasalDuration", 
    "_description": "TempBasalDuration 2016-03-22T22:57:36 head[2], body[0] op[0x16]", 
    "timestamp": "2016-03-22T22:57:36-07:00", 
    "_body": "", 
    "_head": "1601", 
    "duration (min)": 30, 
    "_date": "24f9165610"
  }, 
  {
    "_type": "TempBasal", 
    "temp": "absolute", 
    "_description": "TempBasal 2016-03-22T22:57:36 head[2], body[1] op[0x33]", 
    "timestamp": "2016-03-22T22:57:36-07:00", 
    "_body": "00", 
    "_head": "3308", 
    "rate": 0.2, 
    "_date": "24f9165610"
  }, 
  {
    "_type": "TempBasalDuration", 
    "_description": "TempBasalDuration 2016-03-22T22:43:16 head[2], body[0] op[0x16]", 
    "timestamp": "2016-03-22T22:43:16-07:00", 
    "_body": "", 
    "_head": "1601", 
    "duration (min)": 30, 
    "_date": "10eb165610"
  }, 
  {
    "_type": "TempBasal", 
    "temp": "absolute", 
    "_description": "TempBasal 2016-03-22T22:43:16 head[2], body[1] op[0x33]", 
    "timestamp": "2016-03-22T22:43:16-07:00", 
    "_body": "00", 
    "_head": "331e", 
    "rate": 0.75, 
    "_date": "10eb165610"
  }, 
  {
    "_type": "TempBasalDuration", 
    "_description": "TempBasalDuration 2016-03-22T22:43:14 head[2], body[0] op[0x16]", 
    "timestamp": "2016-03-22T22:43:14-07:00", 
    "_body": "", 
    "_head": "1601", 
    "duration (min)": 30, 
    "_date": "0eeb165610"
  }, 
  {
    "_type": "TempBasal", 
    "temp": "absolute", 
    "_description": "TempBasal 2016-03-22T22:43:14 head[2], body[1] op[0x33]", 
    "timestamp": "2016-03-22T22:43:14-07:00", 
    "_body": "00", 
    "_head": "331e", 
    "rate": 0.75, 
    "_date": "0eeb165610"
  }, 
  {
    "_type": "TempBasalDuration", 
    "_description": "TempBasalDuration 2016-03-22T22:43:12 head[2], body[0] op[0x16]", 
    "timestamp": "2016-03-22T22:43:12-07:00", 
    "_body": "", 
    "_head": "1601", 
    "duration (min)": 30, 
    "_date": "0ceb165610"
  }, 
  {
    "_type": "TempBasal", 
    "temp": "absolute", 
    "_description": "TempBasal 2016-03-22T22:43:12 head[2], body[1] op[0x33]", 
    "timestamp": "2016-03-22T22:43:12-07:00", 
    "_body": "00", 
    "_head": "331e", 
    "rate": 0.75, 
    "_date": "0ceb165610"
  }, 
  {
    "_type": "TempBasalDuration", 
    "_description": "TempBasalDuration 2016-03-22T22:34:10 head[2], body[0] op[0x16]", 
    "timestamp": "2016-03-22T22:34:10-07:00", 
    "_body": "", 
    "_head": "1601", 
    "duration (min)": 30, 
    "_date": "0ae2165610"
  }, 
  {
    "_type": "TempBasal", 
    "temp": "absolute", 
    "_description": "TempBasal 2016-03-22T22:34:10 head[2], body[1] op[0x33]", 
    "timestamp": "2016-03-22T22:34:10-07:00", 
    "_body": "00", 
    "_head": "332a", 
    "rate": 1.05, 
    "_date": "0ae2165610"
  }, 
  {
    "_type": "TempBasalDuration", 
    "_description": "TempBasalDuration 2016-03-22T22:34:07 head[2], body[0] op[0x16]", 
    "timestamp": "2016-03-22T22:34:07-07:00", 
    "_body": "", 
    "_head": "1601", 
    "duration (min)": 30, 
    "_date": "07e2165610"
  }, 
  {
    "_type": "TempBasal", 
    "temp": "absolute", 
    "_description": "TempBasal 2016-03-22T22:34:07 head[2], body[1] op[0x33]", 
    "timestamp": "2016-03-22T22:34:07-07:00", 
    "_body": "00", 
    "_head": "332a", 
    "rate": 1.05, 
    "_date": "07e2165610"
  }, 
  {
    "_type": "TempBasalDuration", 
    "_description": "TempBasalDuration 2016-03-22T22:34:06 head[2], body[0] op[0x16]", 
    "timestamp": "2016-03-22T22:34:06-07:00", 
    "_body": "", 
    "_head": "1601", 
    "duration (min)": 30, 
    "_date": "06e2165610"
  }, 
  {
    "_type": "TempBasal", 
    "temp": "absolute", 
    "_description": "TempBasal 2016-03-22T22:34:06 head[2], body[1] op[0x33]", 
    "timestamp": "2016-03-22T22:34:06-07:00", 
    "_body": "00", 
    "_head": "332a", 
    "rate": 1.05, 
    "_date": "06e2165610"
  }, 
  {
    "_type": "TempBasalDuration", 
    "_description": "TempBasalDuration 2016-03-22T22:18:13 head[2], body[0] op[0x16]", 
    "timestamp": "2016-03-22T22:18:13-07:00", 
    "_body": "", 
    "_head": "1601", 
    "duration (min)": 30, 
    "_date": "0dd2165610"
  }, 
  {
    "_type": "TempBasal", 
    "temp": "absolute", 
    "_description": "TempBasal 2016-03-22T22:18:13 head[2], body[1] op[0x33]", 
    "timestamp": "2016-03-22T22:18:13-07:00", 
    "_body": "00", 
    "_head": "3351", 
    "rate": 2.025, 
    "_date": "0dd2165610"
  }, 
  {
    "_type": "TempBasalDuration", 
    "_description": "TempBasalDuration 2016-03-22T22:18:10 head[2], body[0] op[0x16]", 
    "timestamp": "2016-03-22T22:18:10-07:00", 
    "_body": "", 
    "_head": "1601", 
    "duration (min)": 30, 
    "_date": "0ad2165610"
  }, 
  {
    "_type": "TempBasal", 
    "temp": "absolute", 
    "_description": "TempBasal 2016-03-22T22:18:10 head[2], body[1] op[0x33]", 
    "timestamp": "2016-03-22T22:18:10-07:00", 
    "_body": "00", 
    "_head": "3351", 
    "rate": 2.025, 
    "_date": "0ad2165610"
  }, 
  {
    "_type": "TempBasalDuration", 
    "_description": "TempBasalDuration 2016-03-22T22:18:09 head[2], body[0] op[0x16]", 
    "timestamp": "2016-03-22T22:18:09-07:00", 
    "_body": "", 
    "_head": "1601", 
    "duration (min)": 30, 
    "_date": "09d2165610"
  }, 
  {
    "_type": "TempBasal", 
    "temp": "absolute", 
    "_description": "TempBasal 2016-03-22T22:18:09 head[2], body[1] op[0x33]", 
    "timestamp": "2016-03-22T22:18:09-07:00", 
    "_body": "00", 
    "_head": "3351", 
    "rate": 2.025, 
    "_date": "09d2165610"
  }, 
  {
    "_type": "TempBasalDuration", 
    "_description": "TempBasalDuration 2016-03-22T22:12:02 head[2], body[0] op[0x16]", 
    "timestamp": "2016-03-22T22:12:02-07:00", 
    "_body": "", 
    "_head": "1601", 
    "duration (min)": 30, 
    "_date": "02cc165610"
  }, 
  {
    "_type": "TempBasal", 
    "temp": "absolute", 
    "_description": "TempBasal 2016-03-22T22:12:02 head[2], body[1] op[0x33]", 
    "timestamp": "2016-03-22T22:12:02-07:00", 
    "_body": "00", 
    "_head": "3346", 
    "rate": 1.75, 
    "_date": "02cc165610"
  }, 
  {
    "_type": "TempBasalDuration", 
    "_description": "TempBasalDuration 2016-03-22T22:12:00 head[2], body[0] op[0x16]", 
    "timestamp": "2016-03-22T22:12:00-07:00", 
    "_body": "", 
    "_head": "1601", 
    "duration (min)": 30, 
    "_date": "00cc165610"
  }, 
  {
    "_type": "TempBasal", 
    "temp": "absolute", 
    "_description": "TempBasal 2016-03-22T22:12:00 head[2], body[1] op[0x33]", 
    "timestamp": "2016-03-22T22:12:00-07:00", 
    "_body": "00", 
    "_head": "3346", 
    "rate": 1.75, 
    "_date": "00cc165610"
  }, 
  {
    "_type": "TempBasalDuration", 
    "_description": "TempBasalDuration 2016-03-22T22:11:59 head[2], body[0] op[0x16]", 
    "timestamp": "2016-03-22T22:11:59-07:00", 
    "_body": "", 
    "_head": "1601", 
    "duration (min)": 30, 
    "_date": "3bcb165610"
  }, 
  {
    "_type": "TempBasal", 
    "temp": "absolute", 
    "_description": "TempBasal 2016-03-22T22:11:59 head[2], body[1] op[0x33]", 
    "timestamp": "2016-03-22T22:11:59-07:00", 
    "_body": "00", 
    "_head": "3346", 
    "rate": 1.75, 
    "_date": "3bcb165610"
  }, 
  {
    "_type": "TempBasalDuration", 
    "_description": "TempBasalDuration 2016-03-22T21:58:00 head[2], body[0] op[0x16]", 
    "timestamp": "2016-03-22T21:58:00-07:00", 
    "_body": "", 
    "_head": "1601", 
    "duration (min)": 30, 
    "_date": "00fa155610"
  }, 
  {
    "_type": "TempBasal", 
    "temp": "absolute", 
    "_description": "TempBasal 2016-03-22T21:58:00 head[2], body[1] op[0x33]", 
    "timestamp": "2016-03-22T21:58:00-07:00", 
    "_body": "00", 
    "_head": "3341", 
    "rate": 1.625, 
    "_date": "00fa155610"
  }, 
  {
    "_type": "TempBasalDuration", 
    "_description": "TempBasalDuration 2016-03-22T21:57:58 head[2], body[0] op[0x16]", 
    "timestamp": "2016-03-22T21:57:58-07:00", 
    "_body": "", 
    "_head": "1601", 
    "duration (min)": 30, 
    "_date": "3af9155610"
  }, 
  {
    "_type": "TempBasal", 
    "temp": "absolute", 
    "_description": "TempBasal 2016-03-22T21:57:58 head[2], body[1] op[0x33]", 
    "timestamp": "2016-03-22T21:57:58-07:00", 
    "_body": "00", 
    "_head": "3341", 
    "rate": 1.625, 
    "_date": "3af9155610"
  }, 
  {
    "_type": "TempBasalDuration", 
    "_description": "TempBasalDuration 2016-03-22T21:57:56 head[2], body[0] op[0x16]", 
    "timestamp": "2016-03-22T21:57:56-07:00", 
    "_body": "", 
    "_head": "1601", 
    "duration (min)": 30, 
    "_date": "38f9155610"
  }, 
  {
    "_type": "TempBasal", 
    "temp": "absolute", 
    "_description": "TempBasal 2016-03-22T21:57:56 head[2], body[1] op[0x33]", 
    "timestamp": "2016-03-22T21:57:56-07:00", 
    "_body": "00", 
    "_head": "3341", 
    "rate": 1.625, 
    "_date": "38f9155610"
  }, 
  {
    "_type": "TempBasalDuration", 
    "_description": "TempBasalDuration 2016-03-22T21:42:24 head[2], body[0] op[0x16]", 
    "timestamp": "2016-03-22T21:42:24-07:00", 
    "_body": "", 
    "_head": "1601", 
    "duration (min)": 30, 
    "_date": "18ea155610"
  }, 
  {
    "_type": "TempBasal", 
    "temp": "absolute", 
    "_description": "TempBasal 2016-03-22T21:42:24 head[2], body[1] op[0x33]", 
    "timestamp": "2016-03-22T21:42:24-07:00", 
    "_body": "00", 
    "_head": "333c", 
    "rate": 1.5, 
    "_date": "18ea155610"
  }, 
  {
    "_type": "TempBasalDuration", 
    "_description": "TempBasalDuration 2016-03-22T21:42:21 head[2], body[0] op[0x16]", 
    "timestamp": "2016-03-22T21:42:21-07:00", 
    "_body": "", 
    "_head": "1601", 
    "duration (min)": 30, 
    "_date": "15ea155610"
  }, 
  {
    "_type": "TempBasal", 
    "temp": "absolute", 
    "_description": "TempBasal 2016-03-22T21:42:21 head[2], body[1] op[0x33]", 
    "timestamp": "2016-03-22T21:42:21-07:00", 
    "_body": "00", 
    "_head": "333c", 
    "rate": 1.5, 
    "_date": "15ea155610"
  }, 
  {
    "_type": "TempBasalDuration", 
    "_description": "TempBasalDuration 2016-03-22T21:42:20 head[2], body[0] op[0x16]", 
    "timestamp": "2016-03-22T21:42:20-07:00", 
    "_body": "", 
    "_head": "1601", 
    "duration (min)": 30, 
    "_date": "14ea155610"
  }, 
  {
    "_type": "TempBasal", 
    "temp": "absolute", 
    "_description": "TempBasal 2016-03-22T21:42:20 head[2], body[1] op[0x33]", 
    "timestamp": "2016-03-22T21:42:20-07:00", 
    "_body": "00", 
    "_head": "333c", 
    "rate": 1.5, 
    "_date": "14ea155610"
  }, 
  {
    "_type": "TempBasalDuration", 
    "_description": "TempBasalDuration 2016-03-22T21:32:50 head[2], body[0] op[0x16]", 
    "timestamp": "2016-03-22T21:32:50-07:00", 
    "_body": "", 
    "_head": "1601", 
    "duration (min)": 30, 
    "_date": "32e0155610"
  }, 
  {
    "_type": "TempBasal", 
    "temp": "absolute", 
    "_description": "TempBasal 2016-03-22T21:32:50 head[2], body[1] op[0x33]", 
    "timestamp": "2016-03-22T21:32:50-07:00", 
    "_body": "00", 
    "_head": "3332", 
    "rate": 1.25, 
    "_date": "32e0155610"
  }, 
  {
    "_type": "TempBasalDuration", 
    "_description": "TempBasalDuration 2016-03-22T21:32:47 head[2], body[0] op[0x16]", 
    "timestamp": "2016-03-22T21:32:47-07:00", 
    "_body": "", 
    "_head": "1601", 
    "duration (min)": 30, 
    "_date": "2fe0155610"
  }, 
  {
    "_type": "TempBasal", 
    "temp": "absolute", 
    "_description": "TempBasal 2016-03-22T21:32:47 head[2], body[1] op[0x33]", 
    "timestamp": "2016-03-22T21:32:47-07:00", 
    "_body": "00", 
    "_head": "3332", 
    "rate": 1.25, 
    "_date": "2fe0155610"
  }, 
  {
    "_type": "TempBasalDuration", 
    "_description": "TempBasalDuration 2016-03-22T21:32:42 head[2], body[0] op[0x16]", 
    "timestamp": "2016-03-22T21:32:42-07:00", 
    "_body": "", 
    "_head": "1601", 
    "duration (min)": 30, 
    "_date": "2ae0155610"
  }, 
  {
    "_type": "TempBasal", 
    "temp": "absolute", 
    "_description": "TempBasal 2016-03-22T21:32:42 head[2], body[1] op[0x33]", 
    "timestamp": "2016-03-22T21:32:42-07:00", 
    "_body": "00", 
    "_head": "3332", 
    "rate": 1.25, 
    "_date": "2ae0155610"
  }, 
  {
    "_type": "TempBasalDuration", 
    "_description": "TempBasalDuration 2016-03-22T21:22:01 head[2], body[0] op[0x16]", 
    "timestamp": "2016-03-22T21:22:01-07:00", 
    "_body": "", 
    "_head": "1601", 
    "duration (min)": 30, 
    "_date": "01d6155610"
  }, 
  {
    "_type": "TempBasal", 
    "temp": "absolute", 
    "_description": "TempBasal 2016-03-22T21:22:01 head[2], body[1] op[0x33]", 
    "timestamp": "2016-03-22T21:22:01-07:00", 
    "_body": "00", 
    "_head": "3322", 
    "rate": 0.85, 
    "_date": "01d6155610"
  }, 
  {
    "_type": "TempBasalDuration", 
    "_description": "TempBasalDuration 2016-03-22T21:21:59 head[2], body[0] op[0x16]", 
    "timestamp": "2016-03-22T21:21:59-07:00", 
    "_body": "", 
    "_head": "1601", 
    "duration (min)": 30, 
    "_date": "3bd5155610"
  }, 
  {
    "_type": "TempBasal", 
    "temp": "absolute", 
    "_description": "TempBasal 2016-03-22T21:21:59 head[2], body[1] op[0x33]", 
    "timestamp": "2016-03-22T21:21:59-07:00", 
    "_body": "00", 
    "_head": "3322", 
    "rate": 0.85, 
    "_date": "3bd5155610"
  }, 
  {
    "_type": "TempBasalDuration", 
    "_description": "TempBasalDuration 2016-03-22T21:21:58 head[2], body[0] op[0x16]", 
    "timestamp": "2016-03-22T21:21:58-07:00", 
    "_body": "", 
    "_head": "1601", 
    "duration (min)": 30, 
    "_date": "3ad5155610"
  }, 
  {
    "_type": "TempBasal", 
    "temp": "absolute", 
    "_description": "TempBasal 2016-03-22T21:21:58 head[2], body[1] op[0x33]", 
    "timestamp": "2016-03-22T21:21:58-07:00", 
    "_body": "00", 
    "_head": "3322", 
    "rate": 0.85, 
    "_date": "3ad5155610"
  }, 
  {
    "_type": "TempBasalDuration", 
    "_description": "TempBasalDuration 2016-03-22T21:12:09 head[2], body[0] op[0x16]", 
    "timestamp": "2016-03-22T21:12:09-07:00", 
    "_body": "", 
    "_head": "1601", 
    "duration (min)": 30, 
    "_date": "09cc155610"
  }, 
  {
    "_type": "TempBasal", 
    "temp": "absolute", 
    "_description": "TempBasal 2016-03-22T21:12:09 head[2], body[1] op[0x33]", 
    "timestamp": "2016-03-22T21:12:09-07:00", 
    "_body": "00", 
    "_head": "331b", 
    "rate": 0.675, 
    "_date": "09cc155610"
  }, 
  {
    "_type": "TempBasalDuration", 
    "_description": "TempBasalDuration 2016-03-22T21:12:06 head[2], body[0] op[0x16]", 
    "timestamp": "2016-03-22T21:12:06-07:00", 
    "_body": "", 
    "_head": "1601", 
    "duration (min)": 30, 
    "_date": "06cc155610"
  }, 
  {
    "_type": "TempBasal", 
    "temp": "absolute", 
    "_description": "TempBasal 2016-03-22T21:12:06 head[2], body[1] op[0x33]", 
    "timestamp": "2016-03-22T21:12:06-07:00", 
    "_body": "00", 
    "_head": "331b", 
    "rate": 0.675, 
    "_date": "06cc155610"
  }, 
  {
    "_type": "TempBasalDuration", 
    "_description": "TempBasalDuration 2016-03-22T21:12:06 head[2], body[0] op[0x16]", 
    "timestamp": "2016-03-22T21:12:06-07:00", 
    "_body": "", 
    "_head": "1601", 
    "duration (min)": 30, 
    "_date": "06cc155610"
  }, 
  {
    "_type": "TempBasal", 
    "temp": "absolute", 
    "_description": "TempBasal 2016-03-22T21:12:06 head[2], body[1] op[0x33]", 
    "timestamp": "2016-03-22T21:12:06-07:00", 
    "_body": "00", 
    "_head": "331b", 
    "rate": 0.675, 
    "_date": "06cc155610"
  }, 
  {
    "_type": "TempBasalDuration", 
    "_description": "TempBasalDuration 2016-03-22T21:03:52 head[2], body[0] op[0x16]", 
    "timestamp": "2016-03-22T21:03:52-07:00", 
    "_body": "", 
    "_head": "1601", 
    "duration (min)": 30, 
    "_date": "34c3155610"
  }, 
  {
    "_type": "TempBasal", 
    "temp": "absolute", 
    "_description": "TempBasal 2016-03-22T21:03:52 head[2], body[1] op[0x33]", 
    "timestamp": "2016-03-22T21:03:52-07:00", 
    "_body": "00", 
    "_head": "3300", 
    "rate": 0.0, 
    "_date": "34c3155610"
  }, 
  {
    "_type": "TempBasalDuration", 
    "_description": "TempBasalDuration 2016-03-22T21:03:50 head[2], body[0] op[0x16]", 
    "timestamp": "2016-03-22T21:03:50-07:00", 
    "_body": "", 
    "_head": "1601", 
    "duration (min)": 30, 
    "_date": "32c3155610"
  }, 
  {
    "_type": "TempBasal", 
    "temp": "absolute", 
    "_description": "TempBasal 2016-03-22T21:03:50 head[2], body[1] op[0x33]", 
    "timestamp": "2016-03-22T21:03:50-07:00", 
    "_body": "00", 
    "_head": "3300", 
    "rate": 0.0, 
    "_date": "32c3155610"
  }, 
  {
    "_type": "TempBasalDuration", 
    "_description": "TempBasalDuration 2016-03-22T21:03:49 head[2], body[0] op[0x16]", 
    "timestamp": "2016-03-22T21:03:49-07:00", 
    "_body": "", 
    "_head": "1601", 
    "duration (min)": 30, 
    "_date": "31c3155610"
  }, 
  {
    "_type": "TempBasal", 
    "temp": "absolute", 
    "_description": "TempBasal 2016-03-22T21:03:49 head[2], body[1] op[0x33]", 
    "timestamp": "2016-03-22T21:03:49-07:00", 
    "_body": "00", 
    "_head": "3300", 
    "rate": 0.0, 
    "_date": "31c3155610"
  }, 
  {
    "_type": "BGReceived", 
    "_description": "BGReceived 2016-03-22T20:55:52 head[2], body[3] op[0x3f]", 
    "timestamp": "2016-03-22T20:55:52-07:00", 
    "_body": "c23647", 
    "_head": "3f0e", 
    "amount": 114, 
    "link": "c23647", 
    "_date": "34f7547610"
  }, 
  {
    "_type": "CalBGForPH", 
    "_description": "CalBGForPH 2016-03-22T20:55:52 head[2], body[0] op[0x0a]", 
    "timestamp": "2016-03-22T20:55:52-07:00", 
    "_body": "", 
    "_head": "0a72", 
    "amount": 114, 
    "_date": "34f7347610"
  }, 
  {
    "_type": "TempBasalDuration", 
    "_description": "TempBasalDuration 2016-03-22T20:50:16 head[2], body[0] op[0x16]", 
    "timestamp": "2016-03-22T20:50:16-07:00", 
    "_body": "", 
    "_head": "1601", 
    "duration (min)": 30, 
    "_date": "10f2145610"
  }, 
  {
    "_type": "TempBasal", 
    "temp": "absolute", 
    "_description": "TempBasal 2016-03-22T20:50:16 head[2], body[1] op[0x33]", 
    "timestamp": "2016-03-22T20:50:16-07:00", 
    "_body": "00", 
    "_head": "3300", 
    "rate": 0.0, 
    "_date": "10f2145610"
  }, 
  {
    "_type": "TempBasalDuration", 
    "_description": "TempBasalDuration 2016-03-22T20:20:57 head[2], body[0] op[0x16]", 
    "timestamp": "2016-03-22T20:20:57-07:00", 
    "_body": "", 
    "_head": "1601", 
    "duration (min)": 30, 
    "_date": "39d4145610"
  }, 
  {
    "_type": "TempBasal", 
    "temp": "absolute", 
    "_description": "TempBasal 2016-03-22T20:20:57 head[2], body[1] op[0x33]", 
    "timestamp": "2016-03-22T20:20:57-07:00", 
    "_body": "00", 
    "_head": "3300", 
    "rate": 0.0, 
    "_date": "39d4145610"
  }, 
  {
    "_type": "TempBasalDuration", 
    "_description": "TempBasalDuration 2016-03-22T20:20:55 head[2], body[0] op[0x16]", 
    "timestamp": "2016-03-22T20:20:55-07:00", 
    "_body": "", 
    "_head": "1601", 
    "duration (min)": 30, 
    "_date": "37d4145610"
  }, 
  {
    "_type": "TempBasal", 
    "temp": "absolute", 
    "_description": "TempBasal 2016-03-22T20:20:55 head[2], body[1] op[0x33]", 
    "timestamp": "2016-03-22T20:20:55-07:00", 
    "_body": "00", 
    "_head": "3300", 
    "rate": 0.0, 
    "_date": "37d4145610"
  }, 
  {
    "_type": "TempBasalDuration", 
    "_description": "TempBasalDuration 2016-03-22T20:20:53 head[2], body[0] op[0x16]", 
    "timestamp": "2016-03-22T20:20:53-07:00", 
    "_body": "", 
    "_head": "1601", 
    "duration (min)": 30, 
    "_date": "35d4145610"
  }, 
  {
    "_type": "TempBasal", 
    "temp": "absolute", 
    "_description": "TempBasal 2016-03-22T20:20:53 head[2], body[1] op[0x33]", 
    "timestamp": "2016-03-22T20:20:53-07:00", 
    "_body": "00", 
    "_head": "3300", 
    "rate": 0.0, 
    "_date": "35d4145610"
  }, 
  {
    "_type": "TempBasalDuration", 
    "_description": "TempBasalDuration 2016-03-22T20:11:32 head[2], body[0] op[0x16]", 
    "timestamp": "2016-03-22T20:11:32-07:00", 
    "_body": "", 
    "_head": "1601", 
    "duration (min)": 30, 
    "_date": "20cb145610"
  }, 
  {
    "_type": "TempBasal", 
    "temp": "absolute", 
    "_description": "TempBasal 2016-03-22T20:11:32 head[2], body[1] op[0x33]", 
    "timestamp": "2016-03-22T20:11:32-07:00", 
    "_body": "00", 
    "_head": "331b", 
    "rate": 0.675, 
    "_date": "20cb145610"
  }, 
  {
    "_type": "TempBasalDuration", 
    "_description": "TempBasalDuration 2016-03-22T20:11:29 head[2], body[0] op[0x16]", 
    "timestamp": "2016-03-22T20:11:29-07:00", 
    "_body": "", 
    "_head": "1601", 
    "duration (min)": 30, 
    "_date": "1dcb145610"
  }, 
  {
    "_type": "TempBasal", 
    "temp": "absolute", 
    "_description": "TempBasal 2016-03-22T20:11:29 head[2], body[1] op[0x33]", 
    "timestamp": "2016-03-22T20:11:29-07:00", 
    "_body": "00", 
    "_head": "331b", 
    "rate": 0.675, 
    "_date": "1dcb145610"
  }, 
  {
    "_type": "TempBasalDuration", 
    "_description": "TempBasalDuration 2016-03-22T20:11:28 head[2], body[0] op[0x16]", 
    "timestamp": "2016-03-22T20:11:28-07:00", 
    "_body": "", 
    "_head": "1601", 
    "duration (min)": 30, 
    "_date": "1ccb145610"
  }, 
  {
    "_type": "TempBasal", 
    "temp": "absolute", 
    "_description": "TempBasal 2016-03-22T20:11:28 head[2], body[1] op[0x33]", 
    "timestamp": "2016-03-22T20:11:28-07:00", 
    "_body": "00", 
    "_head": "331b", 
    "rate": 0.675, 
    "_date": "1ccb145610"
  }, 
  {
    "_type": "TempBasalDuration", 
    "_description": "TempBasalDuration 2016-03-22T19:52:46 head[2], body[0] op[0x16]", 
    "timestamp": "2016-03-22T19:52:46-07:00", 
    "_body": "", 
    "_head": "1601", 
    "duration (min)": 30, 
    "_date": "2ef4135610"
  }, 
  {
    "_type": "TempBasal", 
    "temp": "absolute", 
    "_description": "TempBasal 2016-03-22T19:52:46 head[2], body[1] op[0x33]", 
    "timestamp": "2016-03-22T19:52:46-07:00", 
    "_body": "00", 
    "_head": "331b", 
    "rate": 0.675, 
    "_date": "2ef4135610"
  }, 
  {
    "_type": "TempBasalDuration", 
    "_description": "TempBasalDuration 2016-03-22T19:47:31 head[2], body[0] op[0x16]", 
    "timestamp": "2016-03-22T19:47:31-07:00", 
    "_body": "", 
    "_head": "1601", 
    "duration (min)": 30, 
    "_date": "1fef135610"
  }, 
  {
    "_type": "TempBasal", 
    "temp": "absolute", 
    "_description": "TempBasal 2016-03-22T19:47:31 head[2], body[1] op[0x33]", 
    "timestamp": "2016-03-22T19:47:31-07:00", 
    "_body": "00", 
    "_head": "332a", 
    "rate": 1.05, 
    "_date": "1fef135610"
  }, 
  {
    "_type": "TempBasalDuration", 
    "_description": "TempBasalDuration 2016-03-22T19:47:29 head[2], body[0] op[0x16]", 
    "timestamp": "2016-03-22T19:47:29-07:00", 
    "_body": "", 
    "_head": "1601", 
    "duration (min)": 30, 
    "_date": "1def135610"
  }, 
  {
    "_type": "TempBasal", 
    "temp": "absolute", 
    "_description": "TempBasal 2016-03-22T19:47:29 head[2], body[1] op[0x33]", 
    "timestamp": "2016-03-22T19:47:29-07:00", 
    "_body": "00", 
    "_head": "332a", 
    "rate": 1.05, 
    "_date": "1def135610"
  }, 
  {
    "_type": "TempBasalDuration", 
    "_description": "TempBasalDuration 2016-03-22T19:44:44 head[2], body[0] op[0x16]", 
    "timestamp": "2016-03-22T19:44:44-07:00", 
    "_body": "", 
    "_head": "1601", 
    "duration (min)": 30, 
    "_date": "2cec135610"
  }, 
  {
    "_type": "TempBasal", 
    "temp": "absolute", 
    "_description": "TempBasal 2016-03-22T19:44:44 head[2], body[1] op[0x33]", 
    "timestamp": "2016-03-22T19:44:44-07:00", 
    "_body": "00", 
    "_head": "331b", 
    "rate": 0.675, 
    "_date": "2cec135610"
  }, 
  {
    "_type": "TempBasalDuration", 
    "_description": "TempBasalDuration 2016-03-22T19:44:41 head[2], body[0] op[0x16]", 
    "timestamp": "2016-03-22T19:44:41-07:00", 
    "_body": "", 
    "_head": "1601", 
    "duration (min)": 30, 
    "_date": "29ec135610"
  }, 
  {
    "_type": "TempBasal", 
    "temp": "absolute", 
    "_description": "TempBasal 2016-03-22T19:44:41 head[2], body[1] op[0x33]", 
    "timestamp": "2016-03-22T19:44:41-07:00", 
    "_body": "00", 
    "_head": "331b", 
    "rate": 0.675, 
    "_date": "29ec135610"
  }, 
  {
    "_type": "TempBasalDuration", 
    "_description": "TempBasalDuration 2016-03-22T19:44:40 head[2], body[0] op[0x16]", 
    "timestamp": "2016-03-22T19:44:40-07:00", 
    "_body": "", 
    "_head": "1601", 
    "duration (min)": 30, 
    "_date": "28ec135610"
  }, 
  {
    "_type": "TempBasal", 
    "temp": "absolute", 
    "_description": "TempBasal 2016-03-22T19:44:40 head[2], body[1] op[0x33]", 
    "timestamp": "2016-03-22T19:44:40-07:00", 
    "_body": "00", 
    "_head": "331b", 
    "rate": 0.675, 
    "_date": "28ec135610"
  }, 
  {
    "_type": "TempBasalDuration", 
    "_description": "TempBasalDuration 2016-03-22T19:38:48 head[2], body[0] op[0x16]", 
    "timestamp": "2016-03-22T19:38:48-07:00", 
    "_body": "", 
    "_head": "1601", 
    "duration (min)": 30, 
    "_date": "30e6135610"
  }, 
  {
    "_type": "TempBasal", 
    "temp": "absolute", 
    "_description": "TempBasal 2016-03-22T19:38:48 head[2], body[1] op[0x33]", 
    "timestamp": "2016-03-22T19:38:48-07:00", 
    "_body": "00", 
    "_head": "335a", 
    "rate": 2.25, 
    "_date": "30e6135610"
  }, 
  {
    "_type": "TempBasalDuration", 
    "_description": "TempBasalDuration 2016-03-22T19:38:45 head[2], body[0] op[0x16]", 
    "timestamp": "2016-03-22T19:38:45-07:00", 
    "_body": "", 
    "_head": "1601", 
    "duration (min)": 30, 
    "_date": "2de6135610"
  }, 
  {
    "_type": "TempBasal", 
    "temp": "absolute", 
    "_description": "TempBasal 2016-03-22T19:38:45 head[2], body[1] op[0x33]", 
    "timestamp": "2016-03-22T19:38:45-07:00", 
    "_body": "00", 
    "_head": "335a", 
    "rate": 2.25, 
    "_date": "2de6135610"
  }, 
  {
    "_type": "TempBasalDuration", 
    "_description": "TempBasalDuration 2016-03-22T19:38:44 head[2], body[0] op[0x16]", 
    "timestamp": "2016-03-22T19:38:44-07:00", 
    "_body": "", 
    "_head": "1601", 
    "duration (min)": 30, 
    "_date": "2ce6135610"
  }, 
  {
    "_type": "TempBasal", 
    "temp": "absolute", 
    "_description": "TempBasal 2016-03-22T19:38:44 head[2], body[1] op[0x33]", 
    "timestamp": "2016-03-22T19:38:44-07:00", 
    "_body": "00", 
    "_head": "335a", 
    "rate": 2.25, 
    "_date": "2ce6135610"
  }, 
  {
    "_type": "Bolus", 
    "_description": "Bolus 2016-03-22T19:31:57 head[8], body[0] op[0x01]", 
    "timestamp": "2016-03-22T19:31:57-07:00", 
    "_body": "", 
    "appended": [
      {
        "_type": "UnabsorbedInsulinBolus", 
        "_description": "UnabsorbedInsulinBolus unknown head[17], body[0] op[0x5c]", 
        "_body": "", 
        "_head": "5c110c17c01649c01653c02a6bd052cfd0", 
        "data": [
          {
            "amount": 0.3, 
            "age": 23
          }, 
          {
            "amount": 0.55, 
            "age": 73
          }, 
          {
            "amount": 0.55, 
            "age": 83
          }, 
          {
            "amount": 1.05, 
            "age": 363
          }, 
          {
            "amount": 2.05, 
            "age": 463
          }
        ], 
        "_date": ""
      }
    ], 
    "programmed": 2.1, 
    "duration": 0, 
    "amount": 2.1, 
    "unabsorbed": 0.9, 
    "_head": "0100540054002400", 
    "type": "normal", 
    "_date": "39df331610"
  }, 
  {
    "_type": "BolusWizard", 
    "bg": 183, 
    "_description": "BolusWizard 2016-03-22T19:31:57 head[2], body[15] op[0x5b]", 
    "timestamp": "2016-03-22T19:31:57-07:00", 
    "_body": "225000a0506e1e0054000024005478", 
    "carb_input": 34, 
    "bg_target_high": 120, 
    "sensitivity": 80, 
    "carb_ratio": 16.0, 
    "food_estimate": 2.1, 
    "unabsorbed_insulin_total": 0.9, 
    "correction_estimate": 0.75, 
    "bg_target_low": 110, 
    "_head": "5bb7", 
    "bolus_estimate": 2.1, 
    "_date": "39df131610"
  }, 
  {
    "_type": "BGReceived", 
    "_description": "BGReceived 2016-03-22T19:31:05 head[2], body[3] op[0x3f]", 
    "timestamp": "2016-03-22T19:31:05-07:00", 
    "_body": "c23647", 
    "_head": "3f16", 
    "amount": 183, 
    "link": "c23647", 
    "_date": "05dff37610"
  }, 
  {
    "_type": "CalBGForPH", 
    "_description": "CalBGForPH 2016-03-22T19:31:05 head[2], body[0] op[0x0a]", 
    "timestamp": "2016-03-22T19:31:05-07:00", 
    "_body": "", 
    "_head": "0ab7", 
    "amount": 183, 
    "_date": "05df337610"
  }, 
  {
    "_type": "BasalProfileStart", 
    "_description": "BasalProfileStart 2016-03-22T19:30:00 head[2], body[3] op[0x7b]", 
    "timestamp": "2016-03-22T19:30:00-07:00", 
    "_body": "271c00", 
    "profile_index": 8, 
    "_head": "7b08", 
    "rate": 0.7, 
    "offset": 70200000, 
    "_date": "00de131610"
  }, 
  {
    "_type": "BasalProfileStart", 
    "_description": "BasalProfileStart 2016-03-22T19:22:01 head[2], body[3] op[0x7b]", 
    "timestamp": "2016-03-22T19:22:01-07:00", 
    "_body": "251400", 
    "profile_index": 7, 
    "_head": "7b07", 
    "rate": 0.5, 
    "offset": 66600000, 
    "_date": "01d6131610"
  }, 
  {
    "programmed": 0.3, 
    "_type": "Bolus", 
    "_description": "Bolus 2016-03-22T19:10:36 head[8], body[0] op[0x01]", 
    "timestamp": "2016-03-22T19:10:36-07:00", 
    "_body": "", 
    "_head": "01000c000c002000", 
    "amount": 0.3, 
    "unabsorbed": 0.8, 
    "duration": 0, 
    "type": "normal", 
    "_date": "24ca337610"
  }, 
  {
    "_type": "TempBasalDuration", 
    "_description": "TempBasalDuration 2016-03-22T18:52:01 head[2], body[0] op[0x16]", 
    "timestamp": "2016-03-22T18:52:01-07:00", 
    "_body": "", 
    "_head": "1601", 
    "duration (min)": 30, 
    "_date": "01f4125610"
  }, 
  {
    "_type": "TempBasal", 
    "temp": "absolute", 
    "_description": "TempBasal 2016-03-22T18:52:01 head[2], body[1] op[0x33]", 
    "timestamp": "2016-03-22T18:52:01-07:00", 
    "_body": "00", 
    "_head": "3314", 
    "rate": 0.5, 
    "_date": "01f4125610"
  }, 
  {
    "_type": "TempBasalDuration", 
    "_description": "TempBasalDuration 2016-03-22T18:52:00 head[2], body[0] op[0x16]", 
    "timestamp": "2016-03-22T18:52:00-07:00", 
    "_body": "", 
    "_head": "1601", 
    "duration (min)": 30, 
    "_date": "00f4125610"
  }, 
  {
    "_type": "TempBasal", 
    "temp": "absolute", 
    "_description": "TempBasal 2016-03-22T18:52:00 head[2], body[1] op[0x33]", 
    "timestamp": "2016-03-22T18:52:00-07:00", 
    "_body": "00", 
    "_head": "3314", 
    "rate": 0.5, 
    "_date": "00f4125610"
  }, 
  {
    "_type": "TempBasalDuration", 
    "_description": "TempBasalDuration 2016-03-22T18:51:59 head[2], body[0] op[0x16]", 
    "timestamp": "2016-03-22T18:51:59-07:00", 
    "_body": "", 
    "_head": "1601", 
    "duration (min)": 30, 
    "_date": "3bf3125610"
  }, 
  {
    "_type": "TempBasal", 
    "temp": "absolute", 
    "_description": "TempBasal 2016-03-22T18:51:59 head[2], body[1] op[0x33]", 
    "timestamp": "2016-03-22T18:51:59-07:00", 
    "_body": "00", 
    "_head": "3314", 
    "rate": 0.5, 
    "_date": "3bf3125610"
  }, 
  {
    "_type": "TempBasalDuration", 
    "_description": "TempBasalDuration 2016-03-22T18:29:10 head[2], body[0] op[0x16]", 
    "timestamp": "2016-03-22T18:29:10-07:00", 
    "_body": "", 
    "_head": "1601", 
    "duration (min)": 30, 
    "_date": "0add125610"
  }, 
  {
    "_type": "TempBasal", 
    "temp": "absolute", 
    "_description": "TempBasal 2016-03-22T18:29:10 head[2], body[1] op[0x33]", 
    "timestamp": "2016-03-22T18:29:10-07:00", 
    "_body": "00", 
    "_head": "3314", 
    "rate": 0.5, 
    "_date": "0add125610"
  }, 
  {
    "_type": "Bolus", 
    "_description": "Bolus 2016-03-22T18:17:37 head[8], body[0] op[0x01]", 
    "timestamp": "2016-03-22T18:17:37-07:00", 
    "_body": "", 
    "appended": [
      {
        "_type": "UnabsorbedInsulinBolus", 
        "_description": "UnabsorbedInsulinBolus unknown head[8], body[0] op[0x5c]", 
        "_body": "", 
        "_head": "5c082a21d05285d0", 
        "data": [
          {
            "amount": 1.05, 
            "age": 289
          }, 
          {
            "amount": 2.05, 
            "age": 389
          }
        ], 
        "_date": ""
      }
    ], 
    "programmed": 1.1, 
    "duration": 0, 
    "amount": 1.1, 
    "unabsorbed": 0.0, 
    "_head": "01002c002c000000", 
    "type": "normal", 
    "_date": "25d1321610"
  }, 
  {
    "_type": "BolusWizard", 
    "bg": 0, 
    "_description": "BolusWizard 2016-03-22T18:17:37 head[2], body[15] op[0x5b]", 
    "timestamp": "2016-03-22T18:17:37-07:00", 
    "_body": "125000a0506e00002c000000002c78", 
    "carb_input": 18, 
    "bg_target_high": 120, 
    "sensitivity": 80, 
    "carb_ratio": 16.0, 
    "food_estimate": 1.1, 
    "unabsorbed_insulin_total": 0.0, 
    "correction_estimate": 0.0, 
    "bg_target_low": 110, 
    "_head": "5b00", 
    "bolus_estimate": 1.1, 
    "_date": "25d1121610"
  }, 
  {
    "_type": "TempBasalDuration", 
    "_description": "TempBasalDuration 2016-03-22T18:06:28 head[2], body[0] op[0x16]", 
    "timestamp": "2016-03-22T18:06:28-07:00", 
    "_body": "", 
    "_head": "1601", 
    "duration (min)": 30, 
    "_date": "1cc6125610"
  }, 
  {
    "_type": "TempBasal", 
    "temp": "absolute", 
    "_description": "TempBasal 2016-03-22T18:06:28 head[2], body[1] op[0x33]", 
    "timestamp": "2016-03-22T18:06:28-07:00", 
    "_body": "00", 
    "_head": "3314", 
    "rate": 0.5, 
    "_date": "1cc6125610"
  }, 
  {
    "_type": "TempBasalDuration", 
    "_description": "TempBasalDuration 2016-03-22T18:06:23 head[2], body[0] op[0x16]", 
    "timestamp": "2016-03-22T18:06:23-07:00", 
    "_body": "", 
    "_head": "1601", 
    "duration (min)": 30, 
    "_date": "17c6125610"
  }, 
  {
    "_type": "TempBasal", 
    "temp": "absolute", 
    "_description": "TempBasal 2016-03-22T18:06:23 head[2], body[1] op[0x33]", 
    "timestamp": "2016-03-22T18:06:23-07:00", 
    "_body": "00", 
    "_head": "3314", 
    "rate": 0.5, 
    "_date": "17c6125610"
  }, 
  {
    "_type": "TempBasalDuration", 
    "_description": "TempBasalDuration 2016-03-22T17:49:04 head[2], body[0] op[0x16]", 
    "timestamp": "2016-03-22T17:49:04-07:00", 
    "_body": "", 
    "_head": "1601", 
    "duration (min)": 30, 
    "_date": "04f1115610"
  }, 
  {
    "_type": "TempBasal", 
    "temp": "absolute", 
    "_description": "TempBasal 2016-03-22T17:49:04 head[2], body[1] op[0x33]", 
    "timestamp": "2016-03-22T17:49:04-07:00", 
    "_body": "00", 
    "_head": "3300", 
    "rate": 0.0, 
    "_date": "04f1115610"
  }, 
  {
    "_type": "TempBasalDuration", 
    "_description": "TempBasalDuration 2016-03-22T17:49:01 head[2], body[0] op[0x16]", 
    "timestamp": "2016-03-22T17:49:01-07:00", 
    "_body": "", 
    "_head": "1601", 
    "duration (min)": 30, 
    "_date": "01f1115610"
  }, 
  {
    "_type": "TempBasal", 
    "temp": "absolute", 
    "_description": "TempBasal 2016-03-22T17:49:01 head[2], body[1] op[0x33]", 
    "timestamp": "2016-03-22T17:49:01-07:00", 
    "_body": "00", 
    "_head": "3300", 
    "rate": 0.0, 
    "_date": "01f1115610"
  }, 
  {
    "_type": "TempBasalDuration", 
    "_description": "TempBasalDuration 2016-03-22T17:49:00 head[2], body[0] op[0x16]", 
    "timestamp": "2016-03-22T17:49:00-07:00", 
    "_body": "", 
    "_head": "1601", 
    "duration (min)": 30, 
    "_date": "00f1115610"
  }, 
  {
    "_type": "TempBasal", 
    "temp": "absolute", 
    "_description": "TempBasal 2016-03-22T17:49:00 head[2], body[1] op[0x33]", 
    "timestamp": "2016-03-22T17:49:00-07:00", 
    "_body": "00", 
    "_head": "3300", 
    "rate": 0.0, 
    "_date": "00f1115610"
  }, 
  {
    "_type": "TempBasalDuration", 
    "_description": "TempBasalDuration 2016-03-22T17:34:59 head[2], body[0] op[0x16]", 
    "timestamp": "2016-03-22T17:34:59-07:00", 
    "_body": "", 
    "_head": "1601", 
    "duration (min)": 30, 
    "_date": "3be2115610"
  }, 
  {
    "_type": "TempBasal", 
    "temp": "absolute", 
    "_description": "TempBasal 2016-03-22T17:34:59 head[2], body[1] op[0x33]", 
    "timestamp": "2016-03-22T17:34:59-07:00", 
    "_body": "00", 
    "_head": "3304", 
    "rate": 0.1, 
    "_date": "3be2115610"
  }, 
  {
    "_type": "TempBasalDuration", 
    "_description": "TempBasalDuration 2016-03-22T17:34:56 head[2], body[0] op[0x16]", 
    "timestamp": "2016-03-22T17:34:56-07:00", 
    "_body": "", 
    "_head": "1601", 
    "duration (min)": 30, 
    "_date": "38e2115610"
  }, 
  {
    "_type": "TempBasal", 
    "temp": "absolute", 
    "_description": "TempBasal 2016-03-22T17:34:56 head[2], body[1] op[0x33]", 
    "timestamp": "2016-03-22T17:34:56-07:00", 
    "_body": "00", 
    "_head": "3304", 
    "rate": 0.1, 
    "_date": "38e2115610"
  }, 
  {
    "_type": "TempBasalDuration", 
    "_description": "TempBasalDuration 2016-03-22T17:34:55 head[2], body[0] op[0x16]", 
    "timestamp": "2016-03-22T17:34:55-07:00", 
    "_body": "", 
    "_head": "1601", 
    "duration (min)": 30, 
    "_date": "37e2115610"
  }, 
  {
    "_type": "TempBasal", 
    "temp": "absolute", 
    "_description": "TempBasal 2016-03-22T17:34:55 head[2], body[1] op[0x33]", 
    "timestamp": "2016-03-22T17:34:55-07:00", 
    "_body": "00", 
    "_head": "3304", 
    "rate": 0.1, 
    "_date": "37e2115610"
  }
]