{
  "device": "openaps://indy-e2", 
  "pump": {
    "battery": {
      "status": "normal", 
      "voltage": 1.46
    }, 
    "status": {
      "status": "normal", 
      "timestamp": "2016-03-23T05:45:37.000Z", 
      "bolusing": false, 
      "suspended": false
    }, 
    "reservoir": 126.75, 
    "clock": "2016-03-22T22:44:41-07:00"
  }, 
  "openaps": {
    "suggested": {
      "bg": 175, 
      "temp": "absolute", 
      "snoozeBG": 115, 
      "timestamp": "2016-03-23T05:47:25.000Z", 
      "reason": "115-115 in range: no temp required, temp 0.75 ~ req 0.75U/hr", 
      "eventualBG": 115, 
      "mealAssist": "Off: Carbs: 0 Boluses: 0 Target: 115 Deviation: 0 BGI: -0.68", 
      "tick": "+0"
    }, 
    "iob": {
      "netbasalinsulin": 0.45, 
      "timestamp": "2016-03-23T05:47:24.000Z", 
      "activity": 0.0017, 
      "basaliob": 0.749, 
      "hightempinsulin": 1.05, 
      "bolussnooze": 0, 
      "iob": 0.749
    }, 
    "enacted": {
      "requested": {
        "duration": 30, 
        "rate": 0.75, 
        "temp": "absolute"
      }, 
      "bg": 175, 
      "temp": "absolute", 
      "snoozeBG": 118, 
      "timestamp": "2016-03-23T05:44:06.000Z", 
      "reason": "Eventual BG 118>110 but Avg. Delta -3.00 < Exp. Delta -0.5; setting current basal of 0.75 as temp", 
      "rate": 0.75, 
      "eventualBG": 118, 
      "recieved": true, 
      "duration": 30, 
      "mealAssist": "Off: Carbs: 0 Boluses: 0 Target: 115 Deviation: 3 BGI: -0.44", 
      "tick": -3
    }
  }, 
  "mmtune": {
    "scanDetails": [
      [
        "916.500", 
        2, 
        -93
      ], 
      [
        "916.520", 
        3, 
        -90
      ], 
      [
        "916.540", 
        4, 
        -86
      ], 
      [
        "916.560", 
        5, 
        -80
      ], 
      [
        "916.580", 
        5, 
        -72
      ], 
      [
        "916.600", 
        5, 
        -66
      ], 
      [
        "916.620", 
        5, 
        -70
      ], 
      [
        "916.640", 
        5, 
        -71
      ], 
      [
        "916.660", 
        5, 
        -71
      ], 
      [
        "916.680", 
        5, 
        -76
      ], 
      [
        "916.700", 
        5, 
        -83
      ], 
      [
        "916.720", 
        2, 
        -95
      ], 
      [
        "916.740", 
        2, 
        -95
      ], 
      [
        "916.760", 
        2, 
        -94
      ], 
      [
        "916.780", 
        2, 
        -95
      ], 
      [
        "916.800", 
        2, 
        -95
      ], 
      [
        "916.820", 
        2, 
        -95
      ]
    ], 
    "setFreq": 916.6, 
    "timestamp": "2016-03-23T05:45:19.000Z", 
    "usedDefault": false
  }
}