{
  "device": "openaps://indy-e2", 
  "pump": {
    "battery": {
      "status": "normal", 
      "voltage": 1.55
    }, 
    "status": {
      "status": "normal", 
      "timestamp": "2016-03-11T08:32:33.000Z", 
      "bolusing": false, 
      "suspended": false
    }, 
    "reservoir": 122.975, 
    "clock": "2016-03-11T00:32:11-08:00"
  }, 
  "openaps": {
    "suggested": {
      "bg": 223, 
      "temp": "absolute", 
      "snoozeBG": 140, 
      "timestamp": "2016-03-11T08:33:32.000Z", 
      "rate": 1.4, 
      "reason": "Eventual BG 140>=120, no temp, setting 1.4U/hr", 
      "eventualBG": 140, 
      "duration": 30, 
      "mealAssist": "On: Carbs: 0 Boluses: 0 Target: 100 Deviation: 27 BGI: -6.12", 
      "tick": "+2"
    }, 
    "iob": {
      "netbasalinsulin": 2.8, 
      "timestamp": "2016-03-11T08:33:31.000Z", 
      "basaliob": 1.374, 
      "activity": 0.0153, 
      "bolussnooze": 0, 
      "iob": 1.374
    }, 
    "enacted": {
      "requested": {
        "duration": 30, 
        "rate": 1.4, 
        "temp": "absolute"
      }, 
      "bg": 223, 
      "temp": "absolute", 
      "snoozeBG": 140, 
      "timestamp": "2016-03-11T08:33:44.000Z", 
      "reason": "Eventual BG 140>=120, no temp, setting 1.4U/hr", 
      "rate": 1.375, 
      "eventualBG": 140, 
      "recieved": true, 
      "duration": 30, 
      "mealAssist": "On: Carbs: 0 Boluses: 0 Target: 100 Deviation: 27 BGI: -6.12", 
      "tick": "+2"
    }
  }, 
  "mmtune": {
    "scanDetails": [
      [
        "916.560", 
        4, 
        -72
      ], 
      [
        "916.580", 
        5, 
        -60
      ], 
      [
        "916.600", 
        5, 
        -59
      ], 
      [
        "916.620", 
        5, 
        -59
      ], 
      [
        "916.640", 
        5, 
        -59
      ], 
      [
        "916.660", 
        5, 
        -60
      ], 
      [
        "916.680", 
        4, 
        -69
      ], 
      [
        "916.700", 
        5, 
        -68
      ], 
      [
        "916.860", 
        1, 
        -97
      ]
    ], 
    "setFreq": 916.64, 
    "timestamp": "2016-03-11T08:32:24.000Z", 
    "usedDefault": false
  }
}