{
  "device": "openaps://indy-e2", 
  "pump": {
    "battery": {
      "status": "normal", 
      "voltage": 1.56
    }, 
    "status": {
      "status": "normal", 
      "timestamp": "2016-03-12T15:08:53.000Z", 
      "bolusing": false, 
      "suspended": false
    }, 
    "reservoir": 139.8, 
    "clock": "2016-03-12T07:08:32-08:00"
  }, 
  "openaps": {
    "suggested": {
      "bg": 120, 
      "temp": "absolute", 
      "snoozeBG": 103, 
      "timestamp": "2016-03-12T15:11:31.000Z", 
      "rate": 0, 
      "reason": "Eventual BG 103<110, setting -0.05U/hr", 
      "eventualBG": 103, 
      "duration": 30, 
      "mealAssist": "Off: Carbs: 0 Boluses: 0 Target: 115 Deviation: -18 BGI: -0.04", 
      "tick": -4
    }, 
    "iob": {
      "netbasalinsulin": -0.25, 
      "timestamp": "2016-03-12T15:11:30.000Z", 
      "basaliob": -0.014, 
      "activity": 0.0001, 
      "bolussnooze": 0, 
      "iob": -0.014
    }, 
    "enacted": {
      "requested": {
        "duration": 30, 
        "rate": 0, 
        "temp": "absolute"
      }, 
      "bg": 120, 
      "temp": "absolute", 
      "snoozeBG": 103, 
      "timestamp": "2016-03-12T15:11:52.000Z", 
      "reason": "Eventual BG 103<110, setting -0.05U/hr", 
      "rate": 0, 
      "eventualBG": 103, 
      "recieved": true, 
      "duration": 30, 
      "mealAssist": "Off: Carbs: 0 Boluses: 0 Target: 115 Deviation: -18 BGI: -0.04", 
      "tick": -4
    }
  }, 
  "mmtune": {
    "scanDetails": [
      [
        "916.560", 
        5, 
        -71
      ], 
      [
        "916.580", 
        5, 
        -67
      ], 
      [
        "916.600", 
        5, 
        -66
      ], 
      [
        "916.620", 
        5, 
        -66
      ], 
      [
        "916.640", 
        5, 
        -65
      ], 
      [
        "916.660", 
        5, 
        -66
      ], 
      [
        "916.680", 
        5, 
        -67
      ], 
      [
        "916.700", 
        5, 
        -76
      ], 
      [
        "916.860", 
        1, 
        -98
      ]
    ], 
    "setFreq": 916.64, 
    "timestamp": "2016-03-12T15:08:36.000Z", 
    "usedDefault": false
  }
}