{
  "device": "openaps://indy-e2", 
  "pump": {
    "battery": {
      "status": "normal", 
      "voltage": 1.58
    }, 
    "status": {
      "status": "normal", 
      "timestamp": "2016-03-19T06:39:11.000Z", 
      "bolusing": false, 
      "suspended": false
    }, 
    "reservoir": 129.075, 
    "clock": "2016-03-18T23:37:54-07:00"
  }, 
  "openaps": {
    "suggested": {
      "bg": 60, 
      "temp": "absolute", 
      "snoozeBG": 98, 
      "timestamp": "2016-03-19T06:37:42.000Z", 
      "reason": "BG 60<80, delta 8>0; no high-temp to cancel", 
      "eventualBG": 98, 
      "mealAssist": "Off: Carbs: 0 Boluses: 0 Target: 115 Deviation: 0 BGI: 1.56", 
      "tick": "+8"
    }, 
    "iob": {
      "netbasalinsulin": -1, 
      "timestamp": "2016-03-19T06:37:42.000Z", 
      "basaliob": -0.477, 
      "activity": -0.0039, 
      "bolussnooze": 0, 
      "iob": -0.477
    }, 
    "enacted": {
      "requested": {
        "duration": 30, 
        "rate": 0, 
        "temp": "absolute"
      }, 
      "bg": 52, 
      "temp": "absolute", 
      "snoozeBG": 62, 
      "timestamp": "2016-03-19T06:34:36.000Z", 
      "reason": "BG 52<80", 
      "rate": 0, 
      "eventualBG": 62, 
      "recieved": true, 
      "duration": 30, 
      "mealAssist": "Off: Carbs: 0 Boluses: 0 Target: 115 Deviation: -22 BGI: 1.6", 
      "tick": "+1"
    }
  }, 
  "mmtune": {
    "scanDetails": [
      [
        "916.560", 
        5, 
        -66
      ], 
      [
        "916.580", 
        5, 
        -59
      ], 
      [
        "916.600", 
        5, 
        -57
      ], 
      [
        "916.620", 
        5, 
        -57
      ], 
      [
        "916.640", 
        5, 
        -57
      ], 
      [
        "916.660", 
        5, 
        -57
      ], 
      [
        "916.680", 
        5, 
        -58
      ], 
      [
        "916.700", 
        5, 
        -62
      ], 
      [
        "916.860", 
        2, 
        -94
      ], 
      [
        "916.900", 
        1, 
        -97
      ]
    ], 
    "setFreq": 916.66, 
    "timestamp": "2016-03-19T06:38:33.000Z", 
    "usedDefault": false
  }
}